ultrasequence/__init__.py
ultrasequence/config.py
ultrasequence/models.py
ultrasequence/parsing.py
ultrasequence/version.py
ultrasequence/bin/__init__.py
ultrasequence/bin/findseq.py
ultrasequence/tests/__init__.py
ultrasequence/tests/test_models.py
ultrasequence/tests/test_parsing.py
ultrasequence-1.0.4.dist-info/METADATA
ultrasequence-1.0.4.dist-info/RECORD
ultrasequence-1.0.4.dist-info/WHEEL
ultrasequence-1.0.4.dist-info/entry_points.txt
ultrasequence-1.0.4.dist-info/top_level.txt
