Metadata-Version: 2.1
Name: ultrasequence
Version: 1.0.4
Summary: An extremely fast file sequencing tool.
Home-page: http://github.com/codycuellar/ultrasequence.git
Author: Cody Cuellar
Author-email: cody.cuellar@gmail.com
License: MIT
Keywords: sequence file parser image ultra frames
Platform: MacOS 10.10
Platform: MacOS 10.11
Platform: MacOS 10.12
Platform: MacOS 10.13
Requires-Python: >=2.7, !=3.0.*, !=3.1.*, !=3.2.*, !=3.3.*, <4
